Metadata-Version: 1.0
Name: em-distributions
Version: 1.0
Summary: Gaussian and Binomial distributions
Home-page: UNKNOWN
Author: Emilio Mantilla
Author-email: emiliomantilla25@gmail.com
License: UNKNOWN
Platform: UNKNOWN
